{
    "CompCell" : {
        "procs"         : 1,
        "x_size"        : 15.0,
        "y_size"        : 50.0,
        "z_size"        : 0.0,
        "res"           : 20,
        "courant"       : 0.5,
        "tLim"          : 200.0,
        "PBC"           : "false"
    },
    "k-point"           : [
        {
            "Y"         : 0,
            "X"         : 0.01666666666
        }
    ],
    "PML" :  [

        {
            "thickness" : 5.00,
            "direction" : "Y"
        }
    ],
    "SourceList"  : [

        {
            "profile"   : "gaussian",
            "fcen"      : 1.0,
            "fwidth"    : 1.0,
            "cutoff"    : 10.00,
            "t_start"   : 0.00,
            "size_y"    : 0.00,
            "size_x"    : 15.00,
            "pol"       : "Ez",
            "loc_y"     : -18.00,
            "loc_x"     : 0.00
        }
    ],
    "ObjectList": [
        {
            "shape"     : "block",
            "loc_y"     : 5.0,
            "loc_x"     : 0.00,
            "size_y"    : 40.0,
            "size_x"    : 50.00,
            "eps"       : 1.00,
            "pols"      : [


            ]
        }
    ],
    "DetectorList"  : [
        {
            "loc_y"     : -14.00,
            "loc_x"     : 0.00,
            "size_y"    : 0.00,
            "size_x"    : 0.00,
            "type"      : "field",
            "pol"       : "Ez"
        },
        {
            "loc_y"     : 0.00,
            "loc_x"     : 0.00,
            "size_y"    : 0.00,
            "size_x"    : 0.00,
            "type"      : "field",
            "pol"       : "Ez"
        },
        {
            "loc_y"     : 15.00,
            "loc_x"     : 0.00,
            "size_y"    : 0.00,
            "size_x"    : 0.00,
            "type"      : "field",
            "pol"       : "Ez"
        },
        {
            "loc_y"     : 19.90,
            "loc_x"     : 0.00,
            "size_y"    : 0.00,
            "size_x"    : 0.00,
            "type"      : "field",
            "pol"       : "Ez"
        }
    ]
}