{
    "CompCell" : {
        "procs"         : 1,
        "x_size"        : 20.0,
        "y_size"        : 20.0,
        "z_size"        : 0.0,
        "res"           : 20,
        "courant"       : 0.5
    },
    "PML" :  [
        {
            "thickness" : 5.0,
            "direction" : "X"
        },
        {
            "thickness" : 5.0,
            "direction" : "Y"
        }
    ],
    "SourceList"  : [
        {
            "profile"   : "gaussian",
            "fcen"      : 3.000,
            "fwidth"    : 1.000,
            "cutoff"    : 16.00,
            "t_start"   : 0.00,
            "size_x"    : 4.00,
            "size_y"    : 4.00,
            "pol"       : "Ez",
            "loc_x"     : 0.00,
            "loc_y"     : 0.00
        }
    ],
    "ObjectList": [ 
    ],
    "DetectorList"  : [
        {
            "loc_x"     : 0.0,
            "loc_y"     : 4.0,
            "size_x"    : 0.00,
            "size_y"    : 0.00,
            "type"      : "field",
            "pol"       : "Ez"
        },
        {
            "loc_x"     : 0.0,
            "loc_y"     : -4.00,
            "size_x"    : 0.00,
            "size_y"    : 0.00,
            "type"      : "field",
            "pol"       : "Ez"
        },
        {
            "loc_x"     : 4.0,
            "loc_y"     : 0.00,
            "size_x"    : 0.00,
            "size_y"    : 0.00,
            "type"      : "field",
            "pol"       : "Ez"
        },
        {
            "loc_x"     : -4.0,
            "loc_y"     : 0.0,
            "size_x"    : 0.00,
            "size_y"    : 0.00,
            "type"      : "field",
            "pol"       : "Ez"
        }
    ]
}
